pypollen/__init__.py
pypollen-0.1.5.dist-info/METADATA
pypollen-0.1.5.dist-info/WHEEL
pypollen-0.1.5.dist-info/top_level.txt
pypollen-0.1.5.dist-info/RECORD
